pdscheduler/__init__.py
pdscheduler/pager_duty.py
pdscheduler/pager_duty_user.py
pdscheduler/schedule_creator.py
pdscheduler/scheduler.py
pdscheduler/validator.py
pdscheduler-0.2.0.dist-info/licenses/LICENSE
pdscheduler-0.2.0.dist-info/METADATA
pdscheduler-0.2.0.dist-info/WHEEL
pdscheduler-0.2.0.dist-info/top_level.txt
pdscheduler-0.2.0.dist-info/RECORD
