Metadata-Version: 2.4
Name: PDscheduler
Version: 0.2.0
Summary: Automatically schedule and upload on-call rotations to PagerDuty from a CSV file
Author: Raphael van den Doel
License: MIT License
Project-URL: Homepage, https://github.com/Raphaelvddoel/pdscheduler
Project-URL: Bug Tracker, https://github.com/Raphaelvddoel/pdscheduler/issues
Classifier: Programming Language :: Python :: 3
Classifier: Programming Language :: Python :: 3.10
Classifier: License :: OSI Approved :: MIT License
Classifier: Operating System :: OS Independent
Requires-Python: >=3.10
License-File: LICENSE
Requires-Dist: pdpyras==4.5.2
Requires-Dist: pytz==2024.2
Requires-Dist: requests==2.32.3
Dynamic: license-file
